Metadata-Version: 2.1
Name: genz-translator
Version: 9023.0.1
Summary: DC Package 
Home-page: https://pypi.org/simple/genz_translator/
Author: Am0Ghost
Author-email: geelpiet5@gmail.com
License: MIT
Download-URL: https://pypi.org/simple/genz_translater/archive/v9023.0.1.tar.gz
Platform: UNKNOWN
